{
  "Qualitaetsbericht": {
    "Einleitung": {
      "Datensatz": {
        "Datum": "2024-11-06",
        "Uhrzeit": "07:33:57",
        "Sprache": "deutsch"
      },
      "Software": {
        "Hersteller": "netfutura GmbH",
        "Produktname": "promato QBM",
        "Version": "2.12"
      },
      "Verantwortlicher_Erstellung": {
        "Kontakt_Person_lang": {
          "Person": {
            "Vorname": "Ines",
            "Nachname": "Graichen",
            "Funktion_Arbeitsschwerpunkt": "Qualitätsmanagementbeauftragte"
          },
          "Telefon": {
            "Vorwahl": "034204",
            "Rufnummer": "87",
            "Durchwahl": "4328"
          },
          "Fax": {
            "Vorwahl": "034204",
            "Rufnummer": "87",
            "Durchwahl": "3602"
          },
          "Email": "Ines.Graichen@skhal.sms.sachsen.de"
        }
      },
      "Verantwortlicher_Krankenhausleitung": {
        "Kontakt_Person_lang": {
          "Person": {
            "Titel": "Dipl. oec.",
            "Vorname": "Doreen",
            "Nachname": "Neu",
            "Funktion_Arbeitsschwerpunkt": "Verwaltungsdirektorin"
          },
          "Telefon": {
            "Vorwahl": "034204",
            "Rufnummer": "87",
            "Durchwahl": "4600"
          },
          "Fax": {
            "Vorwahl": "034204",
            "Rufnummer": "87",
            "Durchwahl": "3602"
          },
          "Email": "Doreen.Neu@skhal.sms.sachsen.de"
        }
      },
      "URL_Internetseite_Krankenhaus": "https://www.skh-altscherbitz.sachsen.de/startseite/",
      "URL_Weitere_Informationen": "https://www.skh-altscherbitz.sachsen.de/ueber_uns/qualitaetsmanagement/"
    },
    "Krankenhaus": {
      "Mehrere_Standorte": {
        "Krankenhauskontaktdaten": {
          "Name": "Sächsisches Krankenhaus Altscherbitz",
          "IK": "261400994",
          "Kontakt_Zugang": {
            "Strasse": "Leipziger Straße",
            "Hausnummer": "59",
            "Postleitzahl": "04435",
            "Ort": "Schkeuditz",
            "URL_Zugang": "http://www.skh-altscherbitz.sachsen.de"
          },
          "Kontakt_Adresse": {
            "Adresse": {
              "Strasse": "Leipziger Straße",
              "Hausnummer": "59"
            },
            "Postleitzahl": "04435",
            "Ort": "Schkeuditz"
          },
          "Telefon": {
            "Vorwahl": "034204",
            "Rufnummer": "870"
          },
          "Email": "poststelle@skhal.sms.sachsen.de",
          "Aerztliche_Leitung": {
            "Kontakt_Person_lang": {
              "Person": {
                "Titel": "Prof. Dr. med.",
                "Vorname": "Peter",
                "Nachname": "Schönknecht",
                "Funktion_Arbeitsschwerpunkt": "Ärztlicher Direktor"
              },
              "Telefon": {
                "Vorwahl": "034204",
                "Rufnummer": "87",
                "Durchwahl": "4306"
              },
              "Fax": {
                "Vorwahl": "034204",
                "Rufnummer": "87",
                "Durchwahl": "2309"
              },
              "Email": "Peter.Schoenknecht@skhal.sms.sachsen.de"
            }
          },
          "Pflegedienstleitung": {
            "Kontakt_Person_lang": {
              "Person": {
                "Vorname": "Julia",
                "Nachname": "Raap",
                "Funktion_Arbeitsschwerpunkt": "stellv. Pflegedirektion"
              },
              "Telefon": {
                "Vorwahl": "034204",
                "Rufnummer": "87",
                "Durchwahl": "4326"
              },
              "Fax": {
                "Vorwahl": "034204",
                "Rufnummer": "87",
                "Durchwahl": "2326"
              },
              "Email": "Julia.Raap@skhal.sms.sachsen.de"
            }
          },
          "Verwaltungsleitung": {
            "Kontakt_Person_lang": {
              "Person": {
                "Titel": "Dipl. oec.",
                "Vorname": "Doreen",
                "Nachname": "Neu",
                "Funktion_Arbeitsschwerpunkt": "Verwaltungsdirektorin"
              },
              "Telefon": {
                "Vorwahl": "034204",
                "Rufnummer": "87",
                "Durchwahl": "4600"
              },
              "Fax": {
                "Vorwahl": "034204",
                "Rufnummer": "87",
                "Durchwahl": "3602"
              },
              "Email": "Doreen.Neu@skhal.sms.sachsen.de"
            }
          }
        },
        "Standortkontaktdaten": {
          "Name": "Sächsisches Krankenhaus Altscherbitz Tagesklinik Standort Eilenburg",
          "IK": "261400994",
          "Standortnummer": "771649000",
          "Standortnummer_alt": "00",
          "Kontakt_Zugang": {
            "Strasse": "Wilhelm-Grune Straße",
            "Hausnummer": "5-8",
            "Postleitzahl": "04838",
            "Ort": "Eilenburg",
            "URL_Zugang": "http://www.skh-altscherbitz.sachsen.de"
          },
          "Kontakt_Adresse": {
            "Adresse": {
              "Strasse": "Wilhelm-Grune-Straße",
              "Hausnummer": "5-8"
            },
            "Postleitzahl": "04838",
            "Ort": "Eilenburg"
          },
          "Aerztliche_Leitung": {
            "Kontakt_Person_lang": {
              "Person": {
                "Titel": "Prof. Dr.med.",
                "Vorname": "Peter",
                "Nachname": "Schönknecht",
                "Funktion_Arbeitsschwerpunkt": "Ärztlicher Direktor"
              },
              "Telefon": {
                "Vorwahl": "034204",
                "Rufnummer": "874306"
              },
              "Fax": {
                "Vorwahl": "034204",
                "Rufnummer": "872309"
              },
              "Email": "Peter.Schoenknecht@skhal.sms.sachsen.de"
            }
          },
          "Pflegedienstleitung": {
            "Kontakt_Person_lang": {
              "Person": {
                "Vorname": "Julia",
                "Nachname": "Raap",
                "Funktion_Arbeitsschwerpunkt": "stellv. Pflegedirektion"
              },
              "Telefon": {
                "Vorwahl": "034204",
                "Rufnummer": "874326"
              },
              "Fax": {
                "Vorwahl": "034204",
                "Rufnummer": "872326"
              },
              "Email": "Julia.Raap@skhal.sms.sachsen.de"
            }
          },
          "Verwaltungsleitung": {
            "Kontakt_Person_lang": {
              "Person": {
                "Titel": "Dipl.oec.",
                "Vorname": "Doreen",
                "Nachname": "Neu",
                "Funktion_Arbeitsschwerpunkt": "Verwaltungsdirektorin"
              },
              "Telefon": {
                "Vorwahl": "034204",
                "Rufnummer": "874600"
              },
              "Fax": {
                "Vorwahl": "034204",
                "Rufnummer": "873602"
              },
              "Email": "Doreen.Neu@skhal.sms.sachsen.de"
            }
          }
        }
      }
    },
    "Krankenhaustraeger": {
      "Name": "Sächsisches Staatsministerium für Soziales und Gesellschaftlichen Zusammenhalt",
      "Krankenhaustraeger_Art": {
        "Art": "öffentlich"
      }
    },
    "Medizinisch_Pflegerische_Leistungsangebote": {
      "MP_Leistungsangebot": [
        {
          "MP_Schluessel": "MP40",
          "Erlaeuterungen": "Wir bieten autogenes Training und progressive Muskelentspannung nach Jacobsen durch Fachpersonal an."
        },
        {
          "MP_Schluessel": "MP52",
          "Erlaeuterungen": "Es gibt verschiedene Kooperationen mit Beratungsstellen und Selbsthilfegruppen. Die Klinik bietet Selbsthilfegruppen diagnosespezifisch strukturiert an, z.B. für Suchtpatienten, Psychosepatienten und neuromuskuläre Erkrankungen.Es besteht regelmäßiger Kontakt zur Parkinson-Selbsthilfegruppe Leipzig."
        },
        {
          "MP_Schluessel": "MP32",
          "Erlaeuterungen": "Diese Leistung wird von unserer ambulant und stationär tätigen Physiotherapieabteilung erbracht."
        },
        {
          "MP_Schluessel": "MP11",
          "Erlaeuterungen": "Wir bieten verschiedene Möglichkeiten an, beispielsweise einen Nordic-Walking-Kurs, etc.."
        },
        {
          "MP_Schluessel": "MP23",
          "Erlaeuterungen": "Die klinische Kunst- und Gestaltungstherapie verstehen wir als Therapie mit künstlerischen Mitteln wie Malen, Zeichnen und plastischem Gestalten. Der Gestaltende erlebt sich als schöpferisch Handelnder, der mit dem Gestaltungsmaterial im experimentellen Spiel Veränderungsprozesse erproben kann."
        },
        {
          "MP_Schluessel": "MP34",
          "Erlaeuterungen": "Für alle klinischen Fachabteilungen stehen  Psychologen zur Verfügung. Es werden auch Problemlösungsgruppen, Stressbewältigungsangebote und psychoonkologische Beratungen in verschiedenen Spezialsprechstunden, angeboten."
        },
        {
          "MP_Schluessel": "MP16",
          "Erlaeuterungen": "Wir bieten unsere ergotherapeutischen Leistungen in stationärer, teilstationärer und ambulanter Form an. In unseren Ergotherapiezentren stehen u. a. eine Holzwerkstatt, eine Töpferei, ein Atelier zur Verfügung."
        },
        {
          "MP_Schluessel": "MP03",
          "Erlaeuterungen": "Wir beraten am Hauptstandort regelmäßig (Rhythmus: 1-2 Monate) Angehörigengruppen in der Allgemeinpsychiatrie und der Gerontopsychiatrie."
        },
        {
          "MP_Schluessel": "MP59",
          "Erlaeuterungen": "Bei  Patienten mit kognitiven Beeinträchtigungen, u. a. computergestütztes Hirnleistungstraining."
        },
        {
          "MP_Schluessel": "MP35",
          "Erlaeuterungen": "Im Zusammenhang mit dem Haltungstraining bieten wir auch Nordic Walking an."
        },
        {
          "MP_Schluessel": "MP63",
          "Erlaeuterungen": "Unser Sozialdienst bietet eine sozialpsychiatrische Beratung an, zu der Zugang auch von extern möglich ist."
        },
        {
          "MP_Schluessel": "MP27",
          "Erlaeuterungen": "Musiktherapie wird in allen Bereichen der Psychiatrie eingesetzt. Die Indikation zur Musiktherapie ergibt sich aus der Diagnose, aus der psychischen Befindlichkeit, den Kommunikationsmöglichkeiten und der Introspektionsfähigkeit der jeweiligen Patienten."
        },
        {
          "MP_Schluessel": "MP08",
          "Erlaeuterungen": "Die Berufs- bzw. Rehabilitationsberatung wird auf allen Stationen durch Sozialtherapeuten durchgeführt."
        },
        {
          "MP_Schluessel": "MP64",
          "Erlaeuterungen": "Intermittierend werden Veranstaltungen (z.B.: Symposien, Tagungen, Vorträge, Fort- und Weiterbildungen, musikalische Veranstaltungen,  etc.) für Patienten, Angehörige und Interessierte organisiert."
        }
      ]
    },
    "Nicht_Medizinische_Leistungsangebote": {
      "NM_Leistungsangebot": [
        {
          "NM_Schluessel": "NM42",
          "Erlaeuterungen": "Am Hauptstandort ist ein bestellter Krankenhausseelsorger für die Patienten da. Organisiert werden u.a. Wochenbeginnandachten in der krankenhauseigenen Kirche am Hauptstandort sowie Konzerte für Patienten und Mitarbeiter in der Krankenhauskirche."
        },
        {
          "NM_Schluessel": "NM60",
          "Erlaeuterungen": "Es besteht eine regelmäßige Zusammenarbeit mit Selbsthilfegruppen und Fachgremien der Stadt Leipzig und Umgebung."
        },
        {
          "NM_Schluessel": "NM49",
          "Erlaeuterungen": "Am Hauptstandort führen wir Informationsveranstaltungen für Patienten, Angehörige und niedergelassene Ärzte durch. Des Weiteren bieten wir medizinische Fortbildungen und Symposien an."
        },
        {
          "NM_Schluessel": "NM66",
          "Erlaeuterungen": "Besondere Ernährungsbedarfe werden bei uns berücksichtigt."
        }
      ]
    },
    "Barrierefreiheit": {
      "Ansprechpartner_Menschen_mit_Beeintraechtigung": {
        "Kontakt_Person_lang": {
          "Person": {
            "Vorname": "Ines",
            "Nachname": "Graichen",
            "Funktion_Arbeitsschwerpunkt": "QM"
          },
          "Telefon": {
            "Vorwahl": "034204",
            "Rufnummer": "874328"
          },
          "Email": "Ines.Graichen@skhal.sms.sachsen.de"
        }
      },
      "Barrierefreiheit_Aspekt": [
        {
          "BF_Schluessel": "BF34",
          "Erlaeuterungen": "Eine Rollstuhlfahrerrampe ist vorhanden."
        },
        {
          "BF_Schluessel": "BF24",
          "Erlaeuterungen": "Wir bieten verschiedene Ernährungsberatungsprogramme  in Einzelbetreuung an."
        },
        {
          "BF_Schluessel": "BF26",
          "Erlaeuterungen": "folgende Fremdsprachen sind möglich: Englisch"
        },
        {
          "BF_Schluessel": "BF10",
          "Erlaeuterungen": "In der Tagesklinik stehen rollstuhlgerechte Toiletten für Besucher und Besucherinnen zur Verfügung."
        },
        {
          "BF_Schluessel": "BF22"
        },
        {
          "BF_Schluessel": "BF08",
          "Erlaeuterungen": "Unsere Serviceeinrichtung ist mit einem rollstuhlgerechten Zugang und einer rollstuhlgerechten Toilette versehen."
        }
      ]
    },
    "Akademische_Lehre": {
      "Akademische_Lehre_Wissenschaftliche_Taetigkeit": [
        {
          "FL_Schluessel": "FL04",
          "Erlaeuterungen": "Teilnahme an wissenschaftlichen Studien, teleradiologische Zusammenarbeit mit der Neuroradiologie der Universität Leipzig"
        },
        {
          "FL_Schluessel": "FL03",
          "Erlaeuterungen": "Studierende der Sozialpädagogik und Sozialen Arbeit können ihre Praktika in unserer Klinik absolvieren, ebenso bieten wir Praktika für Studierende im Master-Studiengang Psychologie an."
        }
      ]
    },
    "Ausbildung_andere_Heilberufe": {
      "Ausbildung_in_anderen_Heilberufen": [
        {
          "HB_Schluessel": "HB17"
        },
        {
          "HB_Schluessel": "HB19",
          "Erlaeuterungen": "32 eigene Ausbildungsplätze und Kooperation mit externen Krankenhaus- und Altenpflegeschulen für die praktische Ausbildung - Pflichteinsätze im Bereich Psychiatrie"
        },
        {
          "HB_Schluessel": "HB01",
          "Erlaeuterungen": "6 eigene Ausbildungsplätze und Kooperation mit externen Krankenhaus- und Altenpflegeschulen für die praktische Ausbildung - Pflichteinsätze im Bereich Psychiatrie"
        }
      ]
    },
    "Anzahl_Betten": "18",
    "Fallzahlen": {
      "Vollstationaere_Fallzahl": "0",
      "Teilstationaere_Fallzahl": "153",
      "Ambulante_Fallzahl": "3669",
      "StaeB_Fallzahl": "0"
    },
    "Personal_des_Krankenhauses": {
      "Aerzte": {
        "Aerzte_ohne_Belegaerzte": {
          "Personalerfassung": {
            "Anzahl_VK": "1,88",
            "Beschaeftigungsverhaeltnis": {
              "Personal_mit_direktem_BV": {
                "Anzahl_VK": "1,88"
              },
              "Personal_ohne_direktem_BV": {
                "Anzahl_VK": "0"
              }
            },
            "Versorgungsform": {
              "Ambulante_Versorgung": {
                "Anzahl_VK": "0,75"
              },
              "Stationaere_Versorgung": {
                "Anzahl_VK": "1,13"
              }
            }
          },
          "Fachaerzte": {
            "Personalerfassung": {
              "Anzahl_VK": "1,88",
              "Beschaeftigungsverhaeltnis": {
                "Personal_mit_direktem_BV": {
                  "Anzahl_VK": "1,88"
                },
                "Personal_ohne_direktem_BV": {
                  "Anzahl_VK": "0"
                }
              },
              "Versorgungsform": {
                "Ambulante_Versorgung": {
                  "Anzahl_VK": "0,75"
                },
                "Stationaere_Versorgung": {
                  "Anzahl_VK": "1,13"
                }
              }
            }
          },
          "Massgebliche_tarifliche_Wochenarbeitszeit": "42,00"
        },
        "Belegaerzte": {
          "Anzahl": "0"
        },
        "Aerzte_ohne_Fachabteilungszuordnung": {
          "Personalerfassung": {
            "Anzahl_VK": "0,00",
            "Beschaeftigungsverhaeltnis": {
              "Personal_mit_direktem_BV": {
                "Anzahl_VK": "0,00"
              },
              "Personal_ohne_direktem_BV": {
                "Anzahl_VK": "0,00"
              }
            },
            "Versorgungsform": {
              "Ambulante_Versorgung": {
                "Anzahl_VK": "0,00"
              },
              "Stationaere_Versorgung": {
                "Anzahl_VK": "0,00"
              }
            }
          },
          "Fachaerzte": {
            "Personalerfassung": {
              "Anzahl_VK": "0,00",
              "Beschaeftigungsverhaeltnis": {
                "Personal_mit_direktem_BV": {
                  "Anzahl_VK": "0,00"
                },
                "Personal_ohne_direktem_BV": {
                  "Anzahl_VK": "0,00"
                }
              },
              "Versorgungsform": {
                "Ambulante_Versorgung": {
                  "Anzahl_VK": "0,00"
                },
                "Stationaere_Versorgung": {
                  "Anzahl_VK": "0,00"
                }
              }
            }
          }
        }
      },
      "Pflegekraefte": {
        "Gesundheits_Krankenpfleger": {
          "Personalerfassung": {
            "Anzahl_VK": "2,88",
            "Beschaeftigungsverhaeltnis": {
              "Personal_mit_direktem_BV": {
                "Anzahl_VK": "2,88"
              },
              "Personal_ohne_direktem_BV": {
                "Anzahl_VK": "0"
              }
            },
            "Versorgungsform": {
              "Ambulante_Versorgung": {
                "Anzahl_VK": "1"
              },
              "Stationaere_Versorgung": {
                "Anzahl_VK": "1,88"
              }
            }
          },
          "Personalerfassung_ohne_Fachabteilungszuordnung": {
            "Anzahl_VK": "0",
            "Beschaeftigungsverhaeltnis": {
              "Personal_mit_direktem_BV": {
                "Anzahl_VK": "0"
              },
              "Personal_ohne_direktem_BV": {
                "Anzahl_VK": "0"
              }
            },
            "Versorgungsform": {
              "Ambulante_Versorgung": {
                "Anzahl_VK": "0"
              },
              "Stationaere_Versorgung": {
                "Anzahl_VK": "0"
              }
            }
          }
        },
        "Massgebliche_tarifliche_Wochenarbeitszeit": "40,00"
      },
      "Ausgewaehltes_Personal_Psych": {
        "Ausgewaehltes_Therapeutisches_Personal": {
          "Psychologische_Psychotherapeuten": {
            "Personalerfassung": {
              "Anzahl_VK": "0,92",
              "Beschaeftigungsverhaeltnis": {
                "Personal_mit_direktem_BV": {
                  "Anzahl_VK": "0,92"
                },
                "Personal_ohne_direktem_BV": {
                  "Anzahl_VK": "0"
                }
              },
              "Versorgungsform": {
                "Ambulante_Versorgung": {
                  "Anzahl_VK": "0,25"
                },
                "Stationaere_Versorgung": {
                  "Anzahl_VK": "0,67"
                }
              }
            }
          },
          "Psychotherapeuten_in_Ausbildung_waehrend_Taetigkeit": {
            "Personalerfassung": {
              "Anzahl_VK": "0,16",
              "Beschaeftigungsverhaeltnis": {
                "Personal_mit_direktem_BV": {
                  "Anzahl_VK": "0,16"
                },
                "Personal_ohne_direktem_BV": {
                  "Anzahl_VK": "0"
                }
              },
              "Versorgungsform": {
                "Ambulante_Versorgung": {
                  "Anzahl_VK": "0"
                },
                "Stationaere_Versorgung": {
                  "Anzahl_VK": "0,16"
                }
              }
            }
          },
          "Ergotherapeuten": {
            "Personalerfassung": {
              "Anzahl_VK": "1,49",
              "Beschaeftigungsverhaeltnis": {
                "Personal_mit_direktem_BV": {
                  "Anzahl_VK": "1,49"
                },
                "Personal_ohne_direktem_BV": {
                  "Anzahl_VK": "0"
                }
              },
              "Versorgungsform": {
                "Ambulante_Versorgung": {
                  "Anzahl_VK": "0,17"
                },
                "Stationaere_Versorgung": {
                  "Anzahl_VK": "1,32"
                }
              }
            }
          },
          "Physiotherapeuten": {
            "Personalerfassung": {
              "Anzahl_VK": "0,88",
              "Beschaeftigungsverhaeltnis": {
                "Personal_mit_direktem_BV": {
                  "Anzahl_VK": "0,88"
                },
                "Personal_ohne_direktem_BV": {
                  "Anzahl_VK": "0"
                }
              },
              "Versorgungsform": {
                "Ambulante_Versorgung": {
                  "Anzahl_VK": "0"
                },
                "Stationaere_Versorgung": {
                  "Anzahl_VK": "0,88"
                }
              }
            }
          }
        }
      },
      "Spezielles_Therapeutisches_Personal": {
        "Therapeutisches_Personal": [
          {
            "SP_Schluessel": "SP13",
            "Personalerfassung": {
              "Anzahl_VK": "0,17",
              "Beschaeftigungsverhaeltnis": {
                "Personal_mit_direktem_BV": {
                  "Anzahl_VK": "0,17"
                },
                "Personal_ohne_direktem_BV": {
                  "Anzahl_VK": "0,00"
                }
              },
              "Versorgungsform": {
                "Ambulante_Versorgung": {
                  "Anzahl_VK": "0,00"
                },
                "Stationaere_Versorgung": {
                  "Anzahl_VK": "0,17"
                }
              }
            }
          },
          {
            "SP_Schluessel": "SP25",
            "Personalerfassung": {
              "Anzahl_VK": "0,63",
              "Beschaeftigungsverhaeltnis": {
                "Personal_mit_direktem_BV": {
                  "Anzahl_VK": "0,63"
                },
                "Personal_ohne_direktem_BV": {
                  "Anzahl_VK": "0,00"
                }
              },
              "Versorgungsform": {
                "Ambulante_Versorgung": {
                  "Anzahl_VK": "0,00"
                },
                "Stationaere_Versorgung": {
                  "Anzahl_VK": "0,63"
                }
              }
            }
          }
        ]
      }
    },
    "Umgang_mit_Risiken_in_der_Patientenversorgung": {
      "Verantwortliche_Person_Qualitaetsmanagement": {
        "Kontakt_Person_lang": {
          "Person": {
            "Vorname": "Ines",
            "Nachname": "Graichen",
            "Funktion_Arbeitsschwerpunkt": "Qualitäts- und Risikomanagement"
          },
          "Telefon": {
            "Vorwahl": "034204",
            "Rufnummer": "87",
            "Durchwahl": "4328"
          },
          "Fax": {
            "Vorwahl": "034204",
            "Rufnummer": "87",
            "Durchwahl": "3602"
          },
          "Email": "Ines.Graichen@skhal.sms.sachsen.de"
        }
      },
      "Lenkungsgremium_Qualitaetsmanagement": {
        "Lenkungsgremium": {
          "Beteiligte_Abteilungen_Funktionsbereiche": "Unser Lenkungsgremium besteht aus einem multiprofessionellen Team, mit Mitarbeiterinnen und Mitarbeitern aus dem ärztlichen und pflegerischen Bereiche, sowie dem Bereich Hygiene und dem administrativen Bereich (Verwaltung, Wirtschaft, Technik).",
          "Tagungsfrequenz": "andere Frequenz"
        }
      },
      "Verantwortliche_Person_Risikomanagement": {
        "Kontakt_Person_lang": {
          "Person": {
            "Vorname": "Ines",
            "Nachname": "Graichen",
            "Funktion_Arbeitsschwerpunkt": "Qualitäts- und Risikomanagement"
          },
          "Telefon": {
            "Vorwahl": "034204",
            "Rufnummer": "87",
            "Durchwahl": "4328"
          },
          "Fax": {
            "Vorwahl": "034204",
            "Rufnummer": "87",
            "Durchwahl": "3602"
          },
          "Email": "Ines.Graichen@skhal.sms.sachsen.de"
        }
      },
      "Lenkungsgremium_Risikomanagement": {
        "Lenkungsgremium": {
          "Beteiligte_Abteilungen_Funktionsbereiche": "Die Mitglieder des Risikoteams sind aus folgenden Funktionsbereichen:  • 2 Mitarbeiter des ärztlichen Dienstes,  • 2 Mitarbeiter des Pflegedienstes,  • 2 Mitarbeiter der Verwaltung,  • 1 Mitarbeiter der IT-Abteilung.",
          "Tagungsfrequenz": "halbjährlich"
        }
      },
      "Instrumente_Massnahmen_Risikomanagement": {
        "Instrument_Massnahme_Risikomanagement": [
          {
            "RM_Schluessel": "RM09",
            "Zusatzangaben_RM": {
              "SOP": {
                "Name": "Dienstanweisung zum Einsatz von Medizinprodukten",
                "Datum": "2024-01-18"
              }
            }
          },
          {
            "RM_Schluessel": "RM04",
            "Zusatzangaben_RM": {
              "SOP": {
                "Name": "Notfallkonzept im stationären, teilstationären und ambulanten Bereich",
                "Datum": "2024-07-16"
              }
            }
          },
          {
            "RM_Schluessel": "RM01",
            "Zusatzangaben_RM": {
              "SOP": {
                "Name": "Konzept Risikomanagement",
                "Datum": "2023-03-10"
              }
            }
          },
          {
            "RM_Schluessel": "RM08",
            "Zusatzangaben_RM": {
              "SOP": {
                "Name": "Standard Freiheitsentziehende Maßnahme",
                "Datum": "2023-06-16"
              }
            }
          },
          {
            "RM_Schluessel": "RM18",
            "Zusatzangaben_RM": {
              "SOP": {
                "Name": "Konzept Entlassungsmanagement",
                "Datum": "2020-04-30"
              }
            }
          },
          {
            "RM_Schluessel": "RM10",
            "Zusatzangaben_RM": {
              "Fallbesprechungen_Konferenzen": {
                "Fallbesprechung_Konferenz": {
                  "Andere": "Alle Fallbesprechungen-/ Konferenzen sind in einer Besprechungsmatrix geregelt."
                }
              }
            }
          },
          {
            "RM_Schluessel": "RM12"
          },
          {
            "RM_Schluessel": "RM07",
            "Zusatzangaben_RM": {
              "SOP": {
                "Name": "Expertenstandard Dekubitusprophylaxe",
                "Datum": "2022-06-23"
              }
            }
          },
          {
            "RM_Schluessel": "RM02"
          },
          {
            "RM_Schluessel": "RM06",
            "Zusatzangaben_RM": {
              "SOP": {
                "Name": "Expertenstandard Sturzprophylaxe",
                "Datum": "2020-08-11"
              }
            }
          }
        ]
      },
      "Einrichtungsinternes_Fehlermeldesystem": {
        "Tagungsgremium": {
          "Tagungsfrequenz": "bei Bedarf"
        },
        "Massnahmen": "bauliche Maßnahmen und Fortführung Projekt digitale Medikation und Kurve",
        "Fehlermeldesystem_intern": {
          "System_intern": {
            "IF_Schluessel": "IF01",
            "Zusatzangaben_IF": {
              "Datum": "2023-03-10"
            }
          }
        }
      },
      "Einrichtungsuebergreifendes_Fehlermeldesystem": {
        "Fehlermeldesystem_uebergreifend": {
          "System_uebergreifend": {
            "EF_Schluessel": "EF03"
          }
        },
        "Tagungsgremium": {
          "Tagungsfrequenz": "bei Bedarf"
        }
      },
      "Hygienepersonal": {
        "Krankenhaushygieniker": {
          "Anzahl": "1",
          "Erlaeuterungen": "Dr. med. Axel Hofmann, externer Krankenhaushygieniker der Landesuntersuchungsanstalt für das Gesundheits- und Veterinärwesen Sachsen (LUA). Die LUA erfüllt Aufgaben, die ihr durch Gesetz, Rechtsverordnung und durch Verwaltungsvorschrift sowie Erlasse des Staatsministeriums für Soziales und Gesellschaftlichen Zusammenhalt übertragen werden."
        },
        "Hygienebeauftragte_Aerzte": {
          "Hygienepersonalerfassung": {
            "Anzahl": "2"
          },
          "Erlaeuterungen": "Herr Pabst,Patrick OA Klinik für Forensische Psychiatrie, Frau Fehre, Stefanie Klinik für Psychiatrie, Psychotherapie und Psychosomatik"
        },
        "Hygienefachkraefte": {
          "Hygienepersonalerfassung": {
            "Anzahl": "1"
          },
          "Erlaeuterungen": "Frau Carmen Pelka (i. Ausb.)"
        },
        "Hygienebeauftragte_Pflege": {
          "Hygienepersonalerfassung": {
            "Anzahl": "2"
          },
          "Erlaeuterungen": "Weitere Hygienebenannte zu den Hygienebeauftragten in der Pflege sind bereichsbezogen vorhanden."
        },
        "Hygienekommission_eingerichtet": {
          "Kontakt_Person_kurz": {
            "Person": {
              "Titel": "Prof. Dr. med.",
              "Vorname": "Peter",
              "Nachname": "Schönknecht",
              "Funktion_Arbeitsschwerpunkt": "Ärztlicher Direktor"
            },
            "Telefon": {
              "Vorwahl": "034204",
              "Rufnummer": "87",
              "Durchwahl": "4306"
            },
            "Fax": {
              "Vorwahl": "034204",
              "Rufnummer": "87",
              "Durchwahl": "2309"
            },
            "Email": "Peter.Schoenknecht@skhal.sms.sachsen.de"
          },
          "Tagungsfrequenz": "halbjährlich"
        }
      },
      "Weitere_Informationen_Hygiene": {
        "Hygienestandard_ZVK": {
          "Standard_Hygiene_ZVK_liegt_vor": {
            "Standard_thematisiert": {
              "Hygienische_Haendedesinfektion": "ja",
              "Hautdesinfektion": "ja",
              "Beachtung_Einwirkzeit": "ja",
              "Anwendung_weiterer_Hygienemassnahmen": {
                "Sterile_Handschuhe": "ja",
                "Steriler_Kittel": "ja",
                "Kopfhaube": "ja",
                "Mund_Nasen_Schutz": "ja",
                "Steriles_Abdecktuch": "ja"
              }
            },
            "Standard_autorisiert": "ja"
          },
          "Standard_Liegedauer_ZVK_liegt_vor": {
            "Standard_autorisiert": "ja"
          }
        },
        "Antibiotikaprophylaxe_Antibiotikatherapie": {
          "Leitlinie_Antibiotikatherapie_liegt_nicht_vor": {},
          "Keine_Durchfuehrung_Operationen": {}
        },
        "Umgang_Wunden": {
          "Standard_Wundversorgung_Verbandwechsel_liegt_vor": {
            "Standard_thematisiert": {
              "Hygienische_Haendedesinfektion": "ja",
              "Verbandwechsel_aseptische_Bedingungen": "ja",
              "Antiseptische_Behandlung_infizierte_Wunden": "ja",
              "Pruefung_Notwendigkeit_Wundauflage": "ja",
              "Meldung_Wundinfektion": "ja"
            },
            "Standard_autorisiert": "ja"
          }
        },
        "Haendedesinfektion": {
          "Haendedesinfektionsmittelverbrauch_Allgemeinstationen_wurde_erhoben": {
            "Haendedesinfektionsmittelverbrauch_Allgemeinstationen": "9,4"
          },
          "Keine_Intensivstation_vorhanden": {},
          "Erfassung_Haendedesinfektionsmittelverbrauch_stationsbezogen": "ja"
        },
        "Umgang_Patienten_MRE": {
          "Standardisierte_Information_MRSA": "ja",
          "Informationsmanagement_MRSA": "ja",
          "Risikoadaptives_Aufnahmescreening": "ja",
          "Regelmaessige_Schulungen": "ja"
        },
        "Hygienebezogenes_Risikomanagement": {
          "Hygiene_Instrument_Massnahme": {
            "HM_Schluessel": "HM09",
            "Zusatzangaben_HM": {
              "Frequenz": "monatlich"
            },
            "Erlaeuterungen": "Es finden monatliche Schulungen zu hygienebezogenen Themen statt. Fortbildungen werden auch in digitaler Form angeboten. Zusätzlich werden 6 verschiedene Themen jeweils 6 - mal pro Jahr angeboten."
          }
        }
      },
      "Beschwerdemanagement": {
        "Strukturiertes_Beschwerdemanagement": {
          "Strukturiertes_Beschwerdemanagement_Eingefuehrt": "ja",
          "Erlaeuterungen": "Unser Krankenhaus verfügt über ein Beschwerdemanagement mit dem Ziel der Planung, Durchführung und Kontrolle aller Maßnahmen, die wir im Zusammenhang mit Beschwerden ergreifen."
        },
        "Schriftliches_Konzept": {
          "Schriftliches_Konzept_Existiert": "ja",
          "Erlaeuterungen": "Es gibt ein schriftliches Konzept Beschwerdemanagement für Patienten, in dem der Nutzen und die Ziele des Beschwerdemanagements, die Beschwerdeannahme und die Beschwerdebearbeitung erläutert sind."
        },
        "Umgang_muendliche_Beschwerden": {
          "Umgang_muendliche_Beschwerden_Geregelt": "ja",
          "Erlaeuterungen": "Zur Annahme von mündlichen Beschwerden existiert ein Beschwerdeannahmeformular.  Das Formular dient zur strukturierten Erfassung von Informationen, die für eine vollständige und schnelle Bearbeitung der Beschwerde benötigt werden."
        },
        "Umgang_schriftliche_Beschwerden": {
          "Umgang_schriftliche_Beschwerden_Geregelt": "ja",
          "Erlaeuterungen": "Schriftliche Beschwerden werden gleichermaßen wie die mündlichen Beschwerden, nach dem Prinzip \"Complaint Ownership\" (Beschwerdebesitzer), als Beschwerde erkannt, erfasst und bearbeitet."
        },
        "Zeitziele_fuer_Rueckmeldung": {
          "Zeitziele_fuer_Rueckmeldung_Definiert": "ja",
          "Erlaeuterungen": "Zur Erfassung und Kontrolle der Rückmeldung an die Beschwerdeführerinnen und Beschwerdeführer haben wir eine Kennzahl definiert."
        },
        "Ansprechpartner": {
          "Ansprechpersonen": {
            "Kontakt_Person_lang": {
              "Person": {
                "Vorname": "Leitenden",
                "Nachname": "Mitarbeiterinnen und Mitarbeiter",
                "Funktion_Arbeitsschwerpunkt": "der Abteilungen und Bereiche"
              },
              "Telefon": {
                "Vorwahl": "034204",
                "Rufnummer": "87",
                "Durchwahl": "0"
              },
              "Fax": {
                "Vorwahl": "034204",
                "Rufnummer": "87",
                "Durchwahl": "3602"
              },
              "Email": "Poststelle@skhal.sms.sachsen.de"
            }
          },
          "Erlaeuterungen": "Das sächsische Krankenhaus Altscherbitz verfolgt ein aktives Beschwerdemanagement. Das bedeutet, dass sich jeder Mitarbeiter in unserer Klinik für die Beschwerden unserer Patienten verpflichtet fühlt. Primär verantwortlich für das Beschwerdemanagement sind unsere Leitenden Mitarbeiter der Abteilungen und Bereiche."
        },
        "Patientenfuersprecher": {
          "Fuersprechpersonen": {
            "Kontakt_Person_lang": {
              "Person": {
                "Vorname": "Rebekka",
                "Nachname": "Krüger",
                "Funktion_Arbeitsschwerpunkt": "Patientenfürsprecherin"
              },
              "Telefon": {
                "Vorwahl": "034204",
                "Rufnummer": "87",
                "Durchwahl": "0"
              },
              "Email": "patientenfuersprecherin.krueger@gmail.com"
            }
          },
          "Erlaeuterungen": "Ein Patientenfürsprecher steht unseren Patientinnen und Patienten an zwei Tagen im Monat vor Ort zur Verfügung. Selbstverständlich können alle Anliegen jederzeit schriftlich oder telefonisch mitgeteilt werden, ein Aushang mit Kontaktdaten befindet sich auf allen Stationen."
        },
        "Anonyme_Eingabemoeglichkeiten": {
          "Anonyme_Eingabemoeglichkeiten_Existieren": "ja",
          "Erlaeuterungen": "Zur anonymen Eingabe von Beschwerden stehen in allen Stationen Briefkästen bereit."
        },
        "Patientenbefragungen": {
          "Patientenbefragungen_Durchgefuehrt": "ja",
          "Erlaeuterungen": "Die persönliche Meinung unserer Patienten, über Ihren Aufenthalt in unserem Krankenhaus ist uns wichtig. Deshalb bekommt jeder Patient einen anonymen Fragebogen zur Beurteilung des Aufenthaltes ausgehändigt."
        },
        "Einweiserbefragungen": {
          "Einweiserbefragungen_Durchgefuehrt": "ja",
          "Erlaeuterungen": "Eine E-Mail Adresse ist eingerichtet, wo jeder niedergelassene Arzt sein Feedback äußern kann.Zusätzliche  finden jährliche Fortbildungsveranstaltungen, fachspezifische Arbeitstreffen mit den niedergelassenen Ärzten statt. ( Klinik trifft Praxis)"
        }
      },
      "Arzneimitteltherapiesicherheit": {
        "Hinweis_Arzneimitteltherapiesicherheit": "AMTS ist die Gesamtheit der Maßnahmen zur Gewährleistung eines optimalen Medikationsprozesses mit dem Ziel, Medikationsfehler und damit vermeidbare Risiken für Patientinnen und Patienten bei der Arzneimitteltherapie zu verringern. Eine Voraussetzung für die erfolgreiche Umsetzung dieser Maßnahmen ist, dass AMTS als integraler Bestandteil der täglichen Routine in einem interdisziplinären und multiprofessionellen Ansatz gelebt wird.",
        "Verantwortliches_Gremium_AMTS": {
          "Arzneimittelkommission": {}
        },
        "Verantwortliche_Person_AMTS": {
          "Verantwortliche_Person_festgelegt": {
            "Eigenstaendige_Position_AMTS": {
              "Kontakt_Person_lang": {
                "Person": {
                  "Titel": "Dr. med.",
                  "Vorname": "Nadine",
                  "Nachname": "Fröhlich",
                  "Funktion_Arbeitsschwerpunkt": "Oberärztin/ Vorsitzende Arzneimittelkommission"
                },
                "Telefon": {
                  "Vorwahl": "034204",
                  "Rufnummer": "87",
                  "Durchwahl": "4332"
                },
                "Fax": {
                  "Vorwahl": "034204",
                  "Rufnummer": "87",
                  "Durchwahl": "2309"
                },
                "Email": "Nadine.Froehlich@skhal.sms.sachsen.de"
              }
            }
          }
        },
        "Pharmazeutisches_Personal": {
          "Anzahl_Apotheker": "0",
          "Anzahl_weiteres_pharmazeutisches_Personal": "0",
          "Erlaeuterungen": "Apotheke Klinikum St. Georg ist Dienstleister für unser Sächsisches Krankenhaus Altscherbitz"
        },
        "Instrumente_Massnahmen_AMTS": {
          "Hinweis_Instrumente_Massnahmen_AMTS": "Die Instrumente und Maßnahmen zur Förderung der Arzneimitteltherapiesicherheit werden mit Fokus auf den typischen Ablauf des Medikationsprozesses bei der stationären Patientenversorgung dargestellt. Eine Besonderheit des Medikationsprozesses im stationären Umfeld stellt das Überleitungsmanagement bei Aufnahme und Entlassung dar. Die im Folgenden gelisteten Instrumente und Maßnahmen adressieren Strukturelemente, z.B. besondere EDV-Ausstattung und Arbeitsmaterialien, sowie Prozessaspekte, wie Arbeitsbeschreibungen für besonders risikobehaftete Prozessschritte bzw. Konzepte zur Sicherung typischer Risikosituationen. Zusätzlich können bewährte Maßnahmen zur Vermeidung von bzw. zum Lernen aus Medikationsfehlern angegeben werden. Das Krankenhaus stellt hier dar, mit welchen Aspekten es sich bereits auseinandergesetzt bzw. welche Maßnahmen es konkret umgesetzt hat. Die folgenden Aspekte können, gegebenenfalls unter Verwendung von Freitextfeldern, dargestellt werden: \n\r - Aufnahme ins Krankenhaus, inklusive Anamnese \n\r Dargestellt werden können Instrumente und Maßnahmen zur Ermittlung der bisherigen Medikation (Arzneimittelanamnese), der anschließenden klinischen Bewertung und der Umstellung auf die im Krankenhaus verfügbare Medikation (Hausliste), sowie zur Dokumentation, sowohl der ursprünglichen Medikation der Patientin oder des Patienten als auch der für die Krankenhausbehandlung angepassten Medikation. \n\r - Medikationsprozess im Krankenhaus \n\r Im vorliegenden Rahmen wird beispielhaft von folgenden Teilprozessen ausgegangen: Arzneimittelanamnese – Verordnung – Patienteninformation – Arzneimittelabgabe – Arzneimittelanwendung – Dokumentation – Therapieüberwachung – Ergebnisbewertung. Dargestellt werden können hierzu Instrumente und Maßnahmen zur sicheren Arzneimittelverordnung, z. B. bezüglich Leserlichkeit, Eindeutigkeit und Vollständigkeit der Dokumentation, aber auch bezüglich Anwendungsgebiet, Wirksamkeit, Nutzen-Risiko-Verhältnis, Verträglichkeit (inklusive potentieller Kontraindikationen, Wechselwirkungen und Ähnliches) und Ressourcenabwägungen. Außerdem können Angaben zur Unterstützung einer zuverlässigen Arzneimittelbestellung, -abgabe und -anwendung bzw. -verabreichung gemacht werden. \n\r - Entlassung \n\r Dargestellt werden können insbesondere die Maßnahmen der Krankenhäuser, die sicherstellen, dass eine strukturierte und sichere Weitergabe von Informationen zur Arzneimitteltherapie an weiterbehandelnde Ärztinnen und Ärzte sowie die angemessene Ausstattung der Patientinnen und Patienten mit Arzneimittelinformationen, Medikationsplan und Medikamenten bzw. Arzneimittelverordnungen erfolgt.",
          "Instrument_Massnahme_AMTS": [
            {
              "AMTS_Schluessel": "AS07"
            },
            {
              "AMTS_Schluessel": "AS12",
              "Zusatzangaben_AMTS": {
                "Massnahmen_Minimierung_Medikationsfehler": {
                  "Massnahme_Minimierung_Medikationsfehler": [
                    {
                      "Massnahme": "Maßnahmen zur Vermeidung von Arzneimittelverwechslung"
                    },
                    {
                      "Massnahme": "Teilnahme an einem einrichtungsübergreifenden Fehlermeldesystem (siehe Kapitel 12.2.3.2)"
                    }
                  ]
                }
              }
            },
            {
              "AMTS_Schluessel": "AS08"
            },
            {
              "AMTS_Schluessel": "AS09",
              "Zusatzangaben_AMTS": {
                "Konzepte_Zubereitung_Arzneimittel": {
                  "Konzept_Zubereitung_Arzneimittel": {
                    "Konzept": "Bereitstellung einer geeigneten Infrastruktur zur Sicherstellung einer fehlerfreien Zubereitung"
                  }
                }
              }
            },
            {
              "AMTS_Schluessel": "AS02"
            },
            {
              "AMTS_Schluessel": "AS01"
            },
            {
              "AMTS_Schluessel": "AS13",
              "Zusatzangaben_AMTS": {
                "Massnahmen_Arzneimitteltherapie_Entlassung": {
                  "Massnahme_Arzneimitteltherapie_Entlassung": [
                    {
                      "Massnahme": "Aushändigung von arzneimittelbezogenen Informationen für die Weiterbehandlung und Anschlussversorgung der Patientin oder des Patienten im Rahmen eines (ggf. vorläufigen) Entlassbriefs"
                    },
                    {
                      "Massnahme": "Aushändigung von Patienteninformationen zur Umsetzung von Therapieempfehlungen"
                    },
                    {
                      "Massnahme": "Aushändigung des Medikationsplans"
                    },
                    {
                      "Massnahme": "bei Bedarf Arzneimittel-Mitgabe oder Ausstellung von Entlassrezepten"
                    }
                  ]
                }
              }
            },
            {
              "AMTS_Schluessel": "AS04"
            },
            {
              "AMTS_Schluessel": "AS11"
            }
          ]
        }
      },
      "Praevention_Hilfe_Missbrauch_Gewalt": {
        "Hinweis_Praevention_Hilfe_Missbrauch_Gewalt": "Gemäß § 4 Absatz 2 der Qualitätsmanagement-Richtlinie haben Einrichtungen die Prävention von und Intervention bei Gewalt und Missbrauch als Teil des einrichtungsinternen Qualitätsmanagements vorzusehen. Ziel ist es, Missbrauch und Gewalt insbesondere gegenüber vulnerablen Patientengruppen, wie beispielsweise Kindern und Jugendlichen oder hilfsbedürftigen Personen, vorzubeugen, zu erkennen, adäquat darauf zu reagieren und auch innerhalb der Einrichtung zu verhindern. Das jeweilige Vorgehen wird an Einrichtungsgröße, Leistungsspektrum und den Patientinnen und Patienten ausgerichtet, um so passgenaue Lösungen zur Sensibilisierung der Teams sowie weitere geeignete vorbeugende und intervenierende Maßnahmen festzulegen. Dies können unter anderem Informationsmaterialien, Kontaktadressen, Schulungen/Fortbildungen, Verhaltenskodizes, Handlungsempfehlungen/Interventionspläne oder umfassende Schutzkonzepte sein.",
        "Praevention_Intervention_Massnahmen": "ja",
        "Schutzkonzepte_Gewalt_Kinder": {
          "Hinweis_Schutzkonzepte_Gewalt_Kinder": "Gemäß § 4 Absatz 2 in Verbindung mit Teil B Abschnitt I § 1 der Qualitätsmanagement-Richtlinie haben sich Einrichtungen, die Kinder und Jugendliche versorgen, gezielt mit der Prävention von und Intervention bei (sexueller) Gewalt und Missbrauch bei Kindern und Jugendlichen zu befassen (Risiko- und Gefährdungsanalyse) und – der Größe und Organisationsform der Einrichtung entsprechend – konkrete Schritte und Maßnahmen abzuleiten (Schutzkonzept). In diesem Abschnitt geben Krankenhäuser, die Kinder und Jugendliche versorgen, an, ob sie gemäß § 4 Absatz 2 in Verbindung mit Teil B Abschnitt I § 1 der Qualitätsmanagement-Richtlinie ein Schutzkonzept gegen (sexuelle) Gewalt bei Kindern und Jugendlichen aufweisen.",
          "Keine_Versorgung_Kinder_Jugendliche": {}
        }
      }
    },
    "Apparative_Ausstattung": {
      "Geraet": [
        {
          "AA_Schluessel": "AA10",
          "Notfallverfuegbarkeit_24h": "nein",
          "Erlaeuterungen": "Wir erstellen an 3 Geräten (stationär und mobil) Nativ-, Langzeit- und Provokations-EEGs mit Schlafentzugs-EEG und Videometrie."
        },
        {
          "AA_Schluessel": "AA43",
          "Notfallverfuegbarkeit_24h": "nein",
          "Erlaeuterungen": "Wir verfügen über einen Messplatz zur Messung feinster elektrischer Potentiale im Nervensystem, die durch Anregung einer der 5 Sinne hervorgerufen wurden."
        },
        {
          "AA_Schluessel": "AA22",
          "Notfallverfuegbarkeit_24h": "ja",
          "Erlaeuterungen": "Schnittbildverfahren mittels starker Magnetfelder und elektromagnetischer Wechselfelder (1,5 Tesla). Die Tischtraglast beträgt 140 kg (bzw. 160 kg ohne Hubbewegung)."
        },
        {
          "AA_Schluessel": "AA08",
          "Notfallverfuegbarkeit_24h": "ja",
          "Erlaeuterungen": "Wir verwenden für das Schichtbildverfahren im Querschnitt mittels Röngenstrahlen einen 128-Zeiler und haben eine Tischtraglast von 295kg."
        }
      ]
    },
    "Teilnahme_Notfallversorgung": {
      "Hinweis_Teilnahme_Notfallversorgung": "Alle Krankenhäuser gewährleisten Notfallversorgung und haben allgemeine Pflichten zur Hilfeleistung im Notfall. Darüber hinaus hat der Gemeinsame Bundesausschuss ein gestuftes System von Notfallstrukturen in Krankenhäusern im entgeltrechtlichen Sinne geregelt. Das bedeutet, dass Krankenhäuser, die festgelegte Anforderungen an eine von drei Notfallstufen erfüllen, durch Vergütungszuschläge finanziell unterstützt werden. Krankenhäuser, die die Anforderungen an eine der drei Stufen nicht erfüllen, erhalten keine Zuschläge. Nimmt ein Krankenhaus nicht am gestuften System von Notfallstrukturen teil und gewährleistet es nicht eine spezielle Notfallversorgung, sieht der Gesetzgeber Abschläge vor.",
      "Teilnahme_Notfallstufe": {
        "Keine_Teilnahme_Notfallversorgung": {}
      },
      "Kooperation_mit_Kassenaerztlicher_Vereinigung": {
        "Notdienstpraxis_Existiert": "nein",
        "Vertragsaerztlicher_Notdienst_Existiert": "nein"
      }
    },
    "Organisationseinheiten_Fachabteilungen": {
      "Organisationseinheit_Fachabteilung": {
        "Gliederungsnummer": "1",
        "Name": "Allgemeine Psychiatrie/Tagesklinik (für teilstationäre Pflegesätze)",
        "Aerztliche_Leitung_OE": {
          "Chefarzt": {
            "Kontakt_Person_lang": {
              "Person": {
                "Titel": "Prof. Dr. med.",
                "Vorname": "Peter",
                "Nachname": "Schönknecht",
                "Funktion_Arbeitsschwerpunkt": "Ärztlicher Direktor des Krankenhauses und Chefarzt der Klinik für Psychiatrie, Psychotherapie und Psychosomatik"
              },
              "Telefon": {
                "Vorwahl": "034204",
                "Rufnummer": "87",
                "Durchwahl": "4306"
              },
              "Fax": {
                "Vorwahl": "034204",
                "Rufnummer": "87",
                "Durchwahl": "2309"
              },
              "Email": "Peter.Schoenknecht@skhal.sms.sachsen.de"
            },
            "Kontakt_Zugang": {
              "Strasse": "Leipziger Straße",
              "Hausnummer": "59",
              "Postleitzahl": "04435",
              "Ort": "Schkeuditz"
            }
          }
        },
        "Zielvereinbarungen": {
          "Zielvereinbarungen_geschlossen_an_Empfehlung_DKG_gehalten": {}
        },
        "Fachabteilungsschluessel": {
          "FA_Schluessel": "2960"
        },
        "Medizinische_Leistungsangebote": {
          "Medizinisches_Leistungsangebot": [
            {
              "VA_VU_Schluessel": "VP15",
              "Erlaeuterungen": "Wir arbeiten störungsspezifisch in verschiedenen Therapiegruppen. Eine kontinuierliche Behandlung ohne Therapeutenwechsel wird gewährleistet. Besonderheiten: DBT - Tagesklinik für emotional instabile Persönlichkeitsstörungen am Haupthaus."
            },
            {
              "VA_VU_Schluessel": "VP05",
              "Erlaeuterungen": "Eine Behandlung ist sowohl stationär, teilstationär und auch ambulant möglich."
            },
            {
              "Sonstiger": {
                "VA_VU_Sonstiger_Schluessel": "VP00",
                "Bezeichnung": "Diagnostik und Therapie von ADHS-Erkrankungen im Erwachsenenalter"
              },
              "Erlaeuterungen": "Die Diagnostik und Therapie ist für Erwachsene ab 18 Jahren gedacht, welche bei sich mögliche Symptome einer AD(H)S vermuten."
            },
            {
              "VA_VU_Schluessel": "VP04",
              "Erlaeuterungen": "Diese Behandlung wird ambulant, teilstationär und stationär angeboten."
            },
            {
              "VA_VU_Schluessel": "VP07",
              "Erlaeuterungen": "Neben den tagesklinischen Therapieangeboten steht auch ein stationärer Spezialbereich mit speziellen Therapieangeboten und unter Einsatz von Heilerziehungspflegern  für Patienten mit geistiger Behinderung."
            },
            {
              "VA_VU_Schluessel": "VP06",
              "Erlaeuterungen": "Diese Behandlung wird ambulant, teilstationär und stationär angeboten."
            },
            {
              "Sonstiger": {
                "VA_VU_Sonstiger_Schluessel": "VP00",
                "Bezeichnung": "Geronto-Psycho-Soziotherapie mit zugehöriger Diagnostik"
              },
              "Erlaeuterungen": "An unserem Hauptstandort besteht ein gerontopsychiatrisches Versorgungszentrum."
            },
            {
              "VA_VU_Schluessel": "VP01",
              "Erlaeuterungen": "Es besteht ein spezifisches Suchtzentrum mit zwei stationären Bereichen und einer angegliederter Tagesklinik für Suchtpatienten."
            },
            {
              "VA_VU_Schluessel": "VP03",
              "Erlaeuterungen": "Eine Behandlung ist sowohl stationär, teilstationär und auch ambulant möglich."
            },
            {
              "VA_VU_Schluessel": "VP08",
              "Erlaeuterungen": "Wir verfügen über einen stationären/ teilstationären Bereich für junge Erwachsene und im Rahmen der ambulanten Betreuung sowie im Früherkennungszentrum erfolgt die Diagnostik durch Fachärzte für Kinder- und Jugendpsychiatrie und -psychotherapie."
            },
            {
              "VA_VU_Schluessel": "VP10",
              "Erlaeuterungen": "An unserem Krankenhaus besteht ein gerontopsychiatrisches Versorgungszentrum mit ambulanter, teilstationärer und stationärer Behandlung und Diagnostik sowie spezielle Gedächtnissprechstunde zur Früherkennung von Demenz."
            },
            {
              "VA_VU_Schluessel": "VP02",
              "Erlaeuterungen": "Diese Behandlung wird ambulant, teilstationär und stationär angeboten. Es besteht ein Früherkennungszentrum für Psychosen am Haupthaus."
            },
            {
              "Sonstiger": {
                "VA_VU_Sonstiger_Schluessel": "VP00",
                "Bezeichnung": "Differenzierte Diagnostik und Therapie von postpartalen Erkrankungen"
              },
              "Erlaeuterungen": "Auch während der Schwangerschaft ist eine Behandlung möglich."
            },
            {
              "Sonstiger": {
                "VA_VU_Sonstiger_Schluessel": "VP00",
                "Bezeichnung": "Psychotherapeutische Richtlinienverfahren"
              },
              "Erlaeuterungen": "Wir führen alle psychotherapeutischen Richtlinienverfahren mit separaten Therapieangeboten durch."
            },
            {
              "VA_VU_Schluessel": "VP11",
              "Erlaeuterungen": "Eine ambulante Versorgung in unserer Psychiatrischen Institutsambulanz wird durch unsere Fachärzte für Kinder- und Jugendpsychiatrie und -psychotherapie angeboten. Wir verfügen jedoch nicht über eine stationäre Kinderpsychiatrie i. e. S."
            }
          ]
        },
        "Fallzahlen_OE": {
          "Vollstationaere_Fallzahl": "0",
          "Teilstationaere_Fallzahl": "153"
        },
        "Hauptdiagnosen": {
          "Keine_Erbracht": {}
        },
        "Prozeduren": {
          "Freiwillige_Angabe": {
            "Prozedur": [
              {
                "OPS_301": "9-649.20",
                "Anzahl": "379"
              },
              {
                "OPS_301": "9-649.40",
                "Anzahl": "242"
              },
              {
                "OPS_301": "9-607",
                "Anzahl": "178"
              },
              {
                "OPS_301": "9-649.42",
                "Anzahl": "158"
              },
              {
                "OPS_301": "9-649.21",
                "Anzahl": "156"
              },
              {
                "OPS_301": "9-649.41",
                "Anzahl": "105"
              },
              {
                "OPS_301": "9-626",
                "Anzahl": "43"
              },
              {
                "OPS_301": "9-649.50",
                "Anzahl": "13"
              },
              {
                "OPS_301": "9-649.30",
                "Anzahl": "11"
              },
              {
                "OPS_301": "3-820",
                "Anzahl": "10"
              },
              {
                "OPS_301": "3-990",
                "Anzahl": "10"
              },
              {
                "OPS_301": "9-649.0",
                "Anzahl": "10"
              },
              {
                "OPS_301": "9-649.51",
                "Anzahl": "10"
              },
              {
                "OPS_301": "9-649.31",
                "Anzahl": "5"
              },
              {
                "OPS_301": "9-649.10",
                "Anzahl": "4"
              },
              {
                "OPS_301": "9-649.43",
                "Anzahl": "4"
              },
              {
                "OPS_301": "1-204.2",
                "Anzahl_Datenschutz": {}
              },
              {
                "OPS_301": "3-802",
                "Anzahl_Datenschutz": {}
              },
              {
                "OPS_301": "6-006.a3",
                "Anzahl_Datenschutz": {}
              },
              {
                "OPS_301": "9-649.11",
                "Anzahl_Datenschutz": {}
              },
              {
                "OPS_301": "9-649.44",
                "Anzahl_Datenschutz": {}
              },
              {
                "OPS_301": "9-649.52",
                "Anzahl_Datenschutz": {}
              },
              {
                "OPS_301": "9-649.53",
                "Anzahl_Datenschutz": {}
              },
              {
                "OPS_301": "9-649.55",
                "Anzahl_Datenschutz": {}
              },
              {
                "OPS_301": "9-649.58",
                "Anzahl_Datenschutz": {}
              },
              {
                "OPS_301": "9-984.6",
                "Anzahl_Datenschutz": {}
              },
              {
                "OPS_301": "9-984.7",
                "Anzahl_Datenschutz": {}
              },
              {
                "OPS_301": "9-984.8",
                "Anzahl_Datenschutz": {}
              }
            ]
          }
        },
        "Ambulante_Behandlungsmoeglichkeiten": {
          "Ambulante_Behandlungsmoeglichkeit": [
            {
              "Ambulanz": {
                "AM_Schluessel": "AM02",
                "Erlaeuterungen": "Folgende Spezialsprechstunden werden angeboten:Stressbewältigungskurs, ambulante Ergotherapie für Erwachsene, psychoth. Vorschaltambulanz, psychoth. Nachsorgegruppe  und Bewegungstherapie."
              }
            },
            {
              "Ambulanz": {
                "AM_Schluessel": "AM02",
                "Bezeichnung": "Versorgungsschwerpunkte im Bereich Psychiatrie/Psychosomatik",
                "Leistungen_Ambulanz": {
                  "Medizinisches_Leistungsangebot": [
                    {
                      "Sonstiger": {
                        "VA_VU_Sonstiger_Schluessel_Ambulanz": "VP00",
                        "Bezeichnung": "Breites Spektrum von psychiatrischer Diagnostik und Therapie von psychisch schwerkranken Patienten im multiprofessionellem Team."
                      }
                    },
                    {
                      "VA_VU_Schluessel_Ambulanz": "VP09"
                    },
                    {
                      "VA_VU_Schluessel_Ambulanz": "VP10"
                    },
                    {
                      "VA_VU_Schluessel_Ambulanz": "VP11"
                    },
                    {
                      "VA_VU_Schluessel_Ambulanz": "VP12"
                    }
                  ]
                },
                "Erlaeuterungen": "VP 11 Diese Behandlungsmöglichkeit wird nur im Kinder und Jugendalter angeboten."
              }
            }
          ]
        },
        "Ambulante_Operationen": {
          "Keine_Erbracht": {}
        },
        "Personelle_Ausstattung": {
          "Aerztliches_Personal": {
            "Hauptabteilung": {
              "Aerzte_ohne_Belegaerzte": {
                "Personalerfassung": {
                  "Anzahl_VK": "1,88",
                  "Beschaeftigungsverhaeltnis": {
                    "Personal_mit_direktem_BV": {
                      "Anzahl_VK": "1,88"
                    },
                    "Personal_ohne_direktem_BV": {
                      "Anzahl_VK": "0,00"
                    }
                  },
                  "Versorgungsform": {
                    "Ambulante_Versorgung": {
                      "Anzahl_VK": "0,75"
                    },
                    "Stationaere_Versorgung": {
                      "Anzahl_VK": "1,13"
                    }
                  }
                },
                "Fachaerzte": {
                  "Personalerfassung": {
                    "Anzahl_VK": "1,88",
                    "Beschaeftigungsverhaeltnis": {
                      "Personal_mit_direktem_BV": {
                        "Anzahl_VK": "1,88"
                      },
                      "Personal_ohne_direktem_BV": {
                        "Anzahl_VK": "0,00"
                      }
                    },
                    "Versorgungsform": {
                      "Ambulante_Versorgung": {
                        "Anzahl_VK": "0,75"
                      },
                      "Stationaere_Versorgung": {
                        "Anzahl_VK": "1,13"
                      }
                    }
                  }
                },
                "Massgebliche_tarifliche_Wochenarbeitszeit": "42,00"
              }
            }
          },
          "Aerztliche_Fachexpertisen": {
            "Fachexpertise": [
              {
                "AQ_ZF_Schluessel": "AQ42"
              },
              {
                "AQ_ZF_Schluessel": "AQ51"
              }
            ]
          },
          "Pflegekraefte": {
            "Gesundheits_Krankenpfleger": {
              "Personalerfassung": {
                "Anzahl_VK": "2,88",
                "Beschaeftigungsverhaeltnis": {
                  "Personal_mit_direktem_BV": {
                    "Anzahl_VK": "2,88"
                  },
                  "Personal_ohne_direktem_BV": {
                    "Anzahl_VK": "0,00"
                  }
                },
                "Versorgungsform": {
                  "Ambulante_Versorgung": {
                    "Anzahl_VK": "1,00"
                  },
                  "Stationaere_Versorgung": {
                    "Anzahl_VK": "1,88"
                  }
                }
              }
            },
            "Massgebliche_tarifliche_Wochenarbeitszeit": "40,00"
          },
          "Pflegerische_Fachexpertisen": {
            "Fachexpertise_Pflege": {
              "PQ_ZP_Schluessel": "PQ05"
            }
          },
          "Ausgewaehltes_Personal_Psych": {
            "Ausgewaehltes_Therapeutisches_Personal": {
              "Diplom_Psychologen": {
                "Personalerfassung": {
                  "Anzahl_VK": "0",
                  "Beschaeftigungsverhaeltnis": {
                    "Personal_mit_direktem_BV": {
                      "Anzahl_VK": "0"
                    },
                    "Personal_ohne_direktem_BV": {
                      "Anzahl_VK": "0"
                    }
                  },
                  "Versorgungsform": {
                    "Ambulante_Versorgung": {
                      "Anzahl_VK": "0"
                    },
                    "Stationaere_Versorgung": {
                      "Anzahl_VK": "0"
                    }
                  }
                }
              },
              "Psychologische_Psychotherapeuten": {
                "Personalerfassung": {
                  "Anzahl_VK": "0,92",
                  "Beschaeftigungsverhaeltnis": {
                    "Personal_mit_direktem_BV": {
                      "Anzahl_VK": "0,92"
                    },
                    "Personal_ohne_direktem_BV": {
                      "Anzahl_VK": "0,00"
                    }
                  },
                  "Versorgungsform": {
                    "Ambulante_Versorgung": {
                      "Anzahl_VK": "0,25"
                    },
                    "Stationaere_Versorgung": {
                      "Anzahl_VK": "0,67"
                    }
                  }
                }
              },
              "Psychotherapeuten_in_Ausbildung_waehrend_Taetigkeit": {
                "Personalerfassung": {
                  "Anzahl_VK": "0,16",
                  "Beschaeftigungsverhaeltnis": {
                    "Personal_mit_direktem_BV": {
                      "Anzahl_VK": "0,16"
                    },
                    "Personal_ohne_direktem_BV": {
                      "Anzahl_VK": "0,00"
                    }
                  },
                  "Versorgungsform": {
                    "Ambulante_Versorgung": {
                      "Anzahl_VK": "0,00"
                    },
                    "Stationaere_Versorgung": {
                      "Anzahl_VK": "0,16"
                    }
                  }
                }
              },
              "Ergotherapeuten": {
                "Personalerfassung": {
                  "Anzahl_VK": "1,49",
                  "Beschaeftigungsverhaeltnis": {
                    "Personal_mit_direktem_BV": {
                      "Anzahl_VK": "1,49"
                    },
                    "Personal_ohne_direktem_BV": {
                      "Anzahl_VK": "0,00"
                    }
                  },
                  "Versorgungsform": {
                    "Ambulante_Versorgung": {
                      "Anzahl_VK": "0,17"
                    },
                    "Stationaere_Versorgung": {
                      "Anzahl_VK": "1,32"
                    }
                  }
                }
              },
              "Physiotherapeuten": {
                "Personalerfassung": {
                  "Anzahl_VK": "0,88",
                  "Beschaeftigungsverhaeltnis": {
                    "Personal_mit_direktem_BV": {
                      "Anzahl_VK": "0,88"
                    },
                    "Personal_ohne_direktem_BV": {
                      "Anzahl_VK": "0,00"
                    }
                  },
                  "Versorgungsform": {
                    "Ambulante_Versorgung": {
                      "Anzahl_VK": "0,00"
                    },
                    "Stationaere_Versorgung": {
                      "Anzahl_VK": "0,88"
                    }
                  }
                }
              }
            }
          }
        }
      }
    },
    "Qualitaetssicherung": {
      "QS_nach_Landesrecht": {
        "Keine_Teilnahme_landesspezifische_Qualitaetssicherungsmassnahme": {}
      },
      "Fortbildung": {
        "Fortbildungspflichtige": "3",
        "Nachweispflichtige": "3",
        "Fortbildungsnachweis_Erbracht_Habende": "3"
      },
      "ATMP-QS-RL": {
        "Hinweis_ATMP-QS-RL": "Krankenhausstandorte, an denen neue Therapien gemäß den Anlagen der ATMP-QS-RL angewendet werden, müssen die dort vorgegebenen Mindestanforderungen an die Struktur-, Prozess- oder Ergebnisqualität erfüllen. Der Medizinische Dienst überprüft die Umsetzung der relevanten Qualitätsanforderungen und stellt dem Krankenhaus eine Bescheinigung aus, wenn diese vollumfänglich erfüllt werden. ATMP nach dieser Richtlinie dürfen ausschließlich von Leistungserbringern angewendet werden, die die Mindestanforderungen erfüllen.",
        "Keine_Anwendung_Arzneimittel_neuartige_Therapien": {}
      }
    }
  }
}